MANIFEST.in
README.md
changelog.md
setup.py
test.py
Bitkub_Api.egg-info/PKG-INFO
Bitkub_Api.egg-info/SOURCES.txt
Bitkub_Api.egg-info/dependency_links.txt
Bitkub_Api.egg-info/requires.txt
Bitkub_Api.egg-info/top_level.txt
venv/lib/python3.8/site-packages/_distutils_hack/__init__.py
venv/lib/python3.8/site-packages/_distutils_hack/override.py
venv/lib/python3.8/site-packages/certifi/__init__.py
venv/lib/python3.8/site-packages/certifi/__main__.py
venv/lib/python3.8/site-packages/certifi/core.py
venv/lib/python3.8/site-packages/chardet/__init__.py
venv/lib/python3.8/site-packages/chardet/big5freq.py
venv/lib/python3.8/site-packages/chardet/big5prober.py
venv/lib/python3.8/site-packages/chardet/chardistribution.py
venv/lib/python3.8/site-packages/chardet/charsetgroupprober.py
venv/lib/python3.8/site-packages/chardet/charsetprober.py
venv/lib/python3.8/site-packages/chardet/codingstatemachine.py
venv/lib/python3.8/site-packages/chardet/compat.py
venv/lib/python3.8/site-packages/chardet/cp949prober.py
venv/lib/python3.8/site-packages/chardet/enums.py
venv/lib/python3.8/site-packages/chardet/escprober.py
venv/lib/python3.8/site-packages/chardet/escsm.py
venv/lib/python3.8/site-packages/chardet/eucjpprober.py
venv/lib/python3.8/site-packages/chardet/euckrfreq.py
venv/lib/python3.8/site-packages/chardet/euckrprober.py
venv/lib/python3.8/site-packages/chardet/euctwfreq.py
venv/lib/python3.8/site-packages/chardet/euctwprober.py
venv/lib/python3.8/site-packages/chardet/gb2312freq.py
venv/lib/python3.8/site-packages/chardet/gb2312prober.py
venv/lib/python3.8/site-packages/chardet/hebrewprober.py
venv/lib/python3.8/site-packages/chardet/jisfreq.py
venv/lib/python3.8/site-packages/chardet/jpcntx.py
venv/lib/python3.8/site-packages/chardet/langbulgarianmodel.py
venv/lib/python3.8/site-packages/chardet/langgreekmodel.py
venv/lib/python3.8/site-packages/chardet/langhebrewmodel.py
venv/lib/python3.8/site-packages/chardet/langhungarianmodel.py
venv/lib/python3.8/site-packages/chardet/langrussianmodel.py
venv/lib/python3.8/site-packages/chardet/langthaimodel.py
venv/lib/python3.8/site-packages/chardet/langturkishmodel.py
venv/lib/python3.8/site-packages/tcp_latency-0.0.10.dist-info/LICENSE.md
