Metadata-Version: 2.1
Name: Bitkub-Api
Version: 0.0.14
Summary: A Non-official very basic Bitkub API
Home-page: https://github.com/l3oatkunGG/bitkub-api
Author: 
Author-email: 
License: MIT
Keywords: Bitkub api
Platform: UNKNOWN
Classifier: Development Status :: 4 - Beta
Classifier: Intended Audience :: Developers
Classifier: Operating System :: Microsoft :: Windows :: Windows 10
Classifier: License :: OSI Approved :: MIT License
Classifier: Programming Language :: Python :: 3
